cmem_plugin_auth/__init__.py
cmem_plugin_auth/workflow/__init__.py
cmem_plugin_auth/workflow/auth.py
cmem_plugin_auth-4.0.0.dist-info/METADATA
cmem_plugin_auth-4.0.0.dist-info/WHEEL
cmem_plugin_auth-4.0.0.dist-info/licenses/LICENSE
cmem_plugin_auth-4.0.0.dist-info/RECORD
